must_cdk_example/__init__.py
must_cdk_example/py.typed
must_cdk_example/_jsii/__init__.py
must_cdk_example/_jsii/example@0.0.0.jsii.tgz
must_cdk_example-0.0.0.dist-info/LICENSE
must_cdk_example-0.0.0.dist-info/METADATA
must_cdk_example-0.0.0.dist-info/WHEEL
must_cdk_example-0.0.0.dist-info/top_level.txt
must_cdk_example-0.0.0.dist-info/RECORD
